mcp_internet_speed_test/__init__.py
mcp_internet_speed_test/main.py
mcp_internet_speed_test-0.1.3.dist-info/licenses/LICENSE
mcp_internet_speed_test-0.1.3.dist-info/METADATA
mcp_internet_speed_test-0.1.3.dist-info/WHEEL
mcp_internet_speed_test-0.1.3.dist-info/entry_points.txt
mcp_internet_speed_test-0.1.3.dist-info/top_level.txt
mcp_internet_speed_test-0.1.3.dist-info/RECORD
