Metadata-Version: 2.4
Name: mcp-internet-speed-test
Version: 0.1.3
Summary: Enables AI models and agents to perform internet speed measurements.
Author-email: Pedro Cruz <hola@inventer.dev>
Maintainer-email: Pedro Cruz <hola@inventer.dev>
Project-URL: Homepage, https://github.com/inventer-dev/mcp-internet-speed-test
Project-URL: Bug Reports, https://github.com/inventer-dev/mcp-internet-speed-test/issues
Project-URL: Source, https://github.com/inventer-dev/mcp-internet-speed-test
Project-URL: Documentation, https://github.com/inventer-dev/mcp-internet-speed-test#readme
Keywords: mcp,speed-test,internet,network,ai,model-context-protocol
Classifier: Development Status :: 4 - Beta
Classifier: Intended Audience :: Developers
Classifier: Programming Language :: Python :: 3
Classifier: Programming Language :: Python :: 3.12
Classifier: License :: OSI Approved :: MIT License
Classifier: Operating System :: OS Independent
Classifier: Topic :: Internet :: WWW/HTTP
Classifier: Topic :: System :: Networking :: Monitoring
Classifier: Topic :: Software Development :: Libraries :: Python Modules
Requires-Python: >=3.12
License-File: LICENSE
Requires-Dist: mcp[cli]>=1.25.0
Requires-Dist: httpx>=0.27.0
Dynamic: license-file
